OnePackLuck/CodeOnePackLuck.py
OnePackLuck/__init__.py
OnePackLuck-0.1.dist-info/LICENSE
OnePackLuck-0.1.dist-info/METADATA
OnePackLuck-0.1.dist-info/WHEEL
OnePackLuck-0.1.dist-info/top_level.txt
OnePackLuck-0.1.dist-info/RECORD
