Metadata-Version: 2.1
Name: OnePackLuck
Version: 0.1
Summary: Procesamiento de imágenes FITS
Home-page: https://github.com/marcelo-marchelini17/OnePackLuck
Author: MArcelo Andrade, Marc Valduz
License-File: LICENSE
Requires-Dist: numpy
Requires-Dist: matplotlib
Requires-Dist: astropy
Requires-Dist: Pillow
